{
	"$schema": "https://schemas.wp.org/trunk/block.json",
	"apiVersion": 3,
	"name": "create-block/icon-list-item",
	"version": "0.1.0",
	"title": "Icon List Item",
	"category": "widgets",
	"icon": "smiley",
	"description": "Example block scaffolded with Create Block tool.",
	"example": {},
	"supports": {
		"html": false
	},
	"attributes": {
		"textContent": {
			"type": "string",
			"default": ""
		},
		"selectedIcon": {
			"type": "string",
			"default": ""
		},
		"itemStyleType": {
			"type": "string",
			"default": "normal"
		},
		"backgroundType": {
			"type": "string",
			"default": "solid"
		},
		"backgroundColor": {
			"type": "string",
			"default": "#fff"
		},
		"backgroundGradient": {
			"type": "string"
		},

		"padding": {
			"type": "number",
			"default": 10
		},
		"paddingTop": {
			"type": "number"
		},
		"paddingRight": {
			"type": "number"
		},
		"paddingLeft": {
			"type": "number"
		},
		"paddingBottom": {
			"type": "number"
		},

		"border": {
			"type": "number",
			"default": 0
		},
		"borderTop": { "type": "number" },
		"borderRight": { "type": "number" },
		"borderBottom": { "type": "number" },
		"borderLeft": { "type": "number" },
		"margin": {
			"type": "number",
			"default": 0
		},
		"marginTop": { "type": "number" },
		"marginRight": { "type": "number" },
		"marginBottom": { "type": "number" },
		"marginLeft": { "type": "number" },

		"borderType": {
			"type": "string",
			"default": "none"
		},

		"borderColor": {
			"type": "string",
			"default": "#2F2F2F"
		},
		"borderRadius": { "type": "number", "default": 0 },
		"borderRadiusTop": { "type": "number" },
		"borderRadiusRight": { "type": "number" },
		"borderRadiusBottom": { "type": "number" },
		"borderRadiusLeft": { "type": "number" },
		"hadBoxShadow": {
			"type": "boolean",
			"default": "none"
		},
		"hoverBackgroundType": { "type": "string", "default": "solid" },
		"hoverBackgroundColor": { "type": "string" },
		"hoverBackgroundGradient": { "type": "string" },

		"hoverBorderType": { "type": "string", "default": "none" },
		"hoverBorderColor": { "type": "string" },

		"hoverBorder": { "type": "number", "default": 0 },
		"hoverBorderTop": { "type": "number" },
		"hoverBorderRight": { "type": "number" },
		"hoverBorderBottom": { "type": "number" },
		"hoverBorderLeft": { "type": "number" },

		"hoverBorderRadius": { "type": "number", "default": 0 },
		"hoverBorderRadiusTop": { "type": "number" },
		"hoverBorderRadiusRight": { "type": "number" },
		"hoverBorderRadiusBottom": { "type": "number" },
		"hoverBorderRadiusLeft": { "type": "number" },

		"hoverHasBoxShadow": { "type": "boolean", "default": false },

		"hoverPadding": { "type": "number", "default": 0 },
		"hoverPaddingTop": { "type": "number" },
		"hoverPaddingRight": { "type": "number" },
		"hoverPaddingBottom": { "type": "number" },
		"hoverPaddingLeft": { "type": "number" }
	},

	"textdomain": "icon-list-item",
	"editorScript": "file:./index.js",
	"editorStyle": "file:./index.css",
	"style": "file:./style-index.css",
	"viewScript": "file:./view.js"
}
